{"kind":"symbol","abstract":[{"type":"text","text":"A view which displays interactive map content."}],"identifier":{"interfaceLanguage":"swift","url":"doc:\/\/com.applayr.MapLayr\/documentation\/MapLayr\/MapView"},"variants":[{"paths":["\/documentation\/maplayr\/mapview"],"traits":[{"interfaceLanguage":"swift"}]}],"seeAlsoSections":[{"anchor":"Essential-Types","title":"Essential Types","identifiers":["doc:\/\/com.applayr.MapLayr\/documentation\/MapLayr\/Map","doc:\/\/com.applayr.MapLayr\/documentation\/MapLayr\/MapViewDelegate"],"generated":true}],"hierarchy":{"paths":[["doc:\/\/com.applayr.MapLayr\/documentation\/MapLayr"]]},"schemaVersion":{"patch":0,"minor":3,"major":0},"sections":[],"relationshipsSections":[{"title":"Inherits From","type":"inheritsFrom","kind":"relationships","identifiers":["doc:\/\/com.applayr.MapLayr\/objc(cs)UIView"]},{"title":"Conforms To","type":"conformsTo","kind":"relationships","identifiers":["doc:\/\/com.applayr.MapLayr\/objc(pl)NSCoding","doc:\/\/com.applayr.MapLayr\/objc(pl)NSObject","doc:\/\/com.applayr.MapLayr\/objc(pl)CALayerDelegate","doc:\/\/com.applayr.MapLayr\/s7CVarArgP","doc:\/\/com.applayr.MapLayr\/s8CopyableP","doc:\/\/com.applayr.MapLayr\/s28CustomDebugStringConvertibleP","doc:\/\/com.applayr.MapLayr\/s23CustomStringConvertibleP","doc:\/\/com.applayr.MapLayr\/SQ","doc:\/\/com.applayr.MapLayr\/SH","doc:\/\/com.applayr.MapLayr\/s8SendableP","doc:\/\/com.applayr.MapLayr\/objc(pl)UIAccessibilityIdentification","doc:\/\/com.applayr.MapLayr\/objc(pl)UIActivityItemsConfigurationProviding","doc:\/\/com.applayr.MapLayr\/objc(pl)UIAppearance","doc:\/\/com.applayr.MapLayr\/objc(pl)UIAppearanceContainer","doc:\/\/com.applayr.MapLayr\/objc(pl)UICoordinateSpace","doc:\/\/com.applayr.MapLayr\/objc(pl)UIDynamicItem","doc:\/\/com.applayr.MapLayr\/objc(pl)UIFocusEnvironment","doc:\/\/com.applayr.MapLayr\/objc(pl)UIFocusItem","doc:\/\/com.applayr.MapLayr\/objc(pl)UIFocusItemContainer","doc:\/\/com.applayr.MapLayr\/objc(pl)UIGestureRecognizerDelegate","doc:\/\/com.applayr.MapLayr\/objc(pl)UILargeContentViewerItem","doc:\/\/com.applayr.MapLayr\/objc(pl)UIPasteConfigurationSupporting","doc:\/\/com.applayr.MapLayr\/objc(pl)UIPopoverPresentationControllerSourceItem","doc:\/\/com.applayr.MapLayr\/objc(pl)UIResponderStandardEditActions","doc:\/\/com.applayr.MapLayr\/5UIKit23UITraitChangeObservableP","doc:\/\/com.applayr.MapLayr\/objc(pl)UITraitEnvironment","doc:\/\/com.applayr.MapLayr\/objc(pl)UIUserActivityRestoring"]}],"topicSections":[{"anchor":"Initializers","title":"Initializers","identifiers":["doc:\/\/com.applayr.MapLayr\/documentation\/MapLayr\/MapView\/init(frame:)"],"generated":true},{"anchor":"Instance-Properties","title":"Instance Properties","identifiers":["doc:\/\/com.applayr.MapLayr\/documentation\/MapLayr\/MapView\/additionalContentInset","doc:\/\/com.applayr.MapLayr\/documentation\/MapLayr\/MapView\/adjustedContentInset","doc:\/\/com.applayr.MapLayr\/documentation\/MapLayr\/MapView\/colorTransformationMode-swift.property","doc:\/\/com.applayr.MapLayr\/documentation\/MapLayr\/MapView\/colorTransformationModeOverride","doc:\/\/com.applayr.MapLayr\/documentation\/MapLayr\/MapView\/colorTransformationPhase","doc:\/\/com.applayr.MapLayr\/documentation\/MapLayr\/MapView\/coordinates","doc:\/\/com.applayr.MapLayr\/documentation\/MapLayr\/MapView\/delegate","doc:\/\/com.applayr.MapLayr\/documentation\/MapLayr\/MapView\/focusedBuildings","doc:\/\/com.applayr.MapLayr\/documentation\/MapLayr\/MapView\/heading","doc:\/\/com.applayr.MapLayr\/documentation\/MapLayr\/MapView\/includeSafeAreaInAdjustedContentInset","doc:\/\/com.applayr.MapLayr\/documentation\/MapLayr\/MapView\/isTransitioningLayers","doc:\/\/com.applayr.MapLayr\/documentation\/MapLayr\/MapView\/lightsMode-swift.property","doc:\/\/com.applayr.MapLayr\/documentation\/MapLayr\/MapView\/lightsModeOverride","doc:\/\/com.applayr.MapLayr\/documentation\/MapLayr\/MapView\/map","doc:\/\/com.applayr.MapLayr\/documentation\/MapLayr\/MapView\/mapData","doc:\/\/com.applayr.MapLayr\/documentation\/MapLayr\/MapView\/mapLayers","doc:\/\/com.applayr.MapLayr\/documentation\/MapLayr\/MapView\/mapPoint","doc:\/\/com.applayr.MapLayr\/documentation\/MapLayr\/MapView\/mapSpan","doc:\/\/com.applayr.MapLayr\/documentation\/MapLayr\/MapView\/mapSpanRange","doc:\/\/com.applayr.MapLayr\/documentation\/MapLayr\/MapView\/orientationProvider","doc:\/\/com.applayr.MapLayr\/documentation\/MapLayr\/MapView\/positionProvider","doc:\/\/com.applayr.MapLayr\/documentation\/MapLayr\/MapView\/shapes","doc:\/\/com.applayr.MapLayr\/documentation\/MapLayr\/MapView\/span","doc:\/\/com.applayr.MapLayr\/documentation\/MapLayr\/MapView\/spanRange","doc:\/\/com.applayr.MapLayr\/documentation\/MapLayr\/MapView\/tilt"],"generated":true},{"anchor":"Instance-Methods","title":"Instance Methods","identifiers":["doc:\/\/com.applayr.MapLayr\/documentation\/MapLayr\/MapView\/addMapLayer(_:)","doc:\/\/com.applayr.MapLayr\/documentation\/MapLayr\/MapView\/addUserLocationMarker(_:)","doc:\/\/com.applayr.MapLayr\/documentation\/MapLayr\/MapView\/angle(at:heading:)-3rwxm","doc:\/\/com.applayr.MapLayr\/documentation\/MapLayr\/MapView\/angle(at:heading:)-9o619","doc:\/\/com.applayr.MapLayr\/documentation\/MapLayr\/MapView\/clearAuxiliaryLayers()","doc:\/\/com.applayr.MapLayr\/documentation\/MapLayr\/MapView\/convert(_:from:)","doc:\/\/com.applayr.MapLayr\/documentation\/MapLayr\/MapView\/convert(_:to:)-18ee4","doc:\/\/com.applayr.MapLayr\/documentation\/MapLayr\/MapView\/convert(_:to:)-1wyv9","doc:\/\/com.applayr.MapLayr\/documentation\/MapLayr\/MapView\/convert(_:to:)-638ab","doc:\/\/com.applayr.MapLayr\/documentation\/MapLayr\/MapView\/convert(_:to:)-93zcu","doc:\/\/com.applayr.MapLayr\/documentation\/MapLayr\/MapView\/convert(_:to:)-br3v","doc:\/\/com.applayr.MapLayr\/documentation\/MapLayr\/MapView\/insertMapLayer(_:at:)","doc:\/\/com.applayr.MapLayr\/documentation\/MapLayr\/MapView\/layoutSubviews()","doc:\/\/com.applayr.MapLayr\/documentation\/MapLayr\/MapView\/moveCamera(coordinates:heading:span:insets:tilt:animated:)-942rx","doc:\/\/com.applayr.MapLayr\/documentation\/MapLayr\/MapView\/moveCamera(coordinates:heading:span:insets:tilt:animated:)-9pbez","doc:\/\/com.applayr.MapLayr\/documentation\/MapLayr\/MapView\/removeMapLayer(_:)","doc:\/\/com.applayr.MapLayr\/documentation\/MapLayr\/MapView\/removeMapLayer(at:)","doc:\/\/com.applayr.MapLayr\/documentation\/MapLayr\/MapView\/removeUserLocationMarker(_:)","doc:\/\/com.applayr.MapLayr\/documentation\/MapLayr\/MapView\/scale(at:)-321bl","doc:\/\/com.applayr.MapLayr\/documentation\/MapLayr\/MapView\/scale(at:)-7ucc8","doc:\/\/com.applayr.MapLayr\/documentation\/MapLayr\/MapView\/setProvider(position:orientation:animated:)","doc:\/\/com.applayr.MapLayr\/documentation\/MapLayr\/MapView\/showLevel(_:)","doc:\/\/com.applayr.MapLayr\/documentation\/MapLayr\/MapView\/traitCollectionDidChange(_:)"],"generated":true},{"anchor":"Enumerations","title":"Enumerations","identifiers":["doc:\/\/com.applayr.MapLayr\/documentation\/MapLayr\/MapView\/ColorTransformationMode-swift.enum","doc:\/\/com.applayr.MapLayr\/documentation\/MapLayr\/MapView\/LightsMode-swift.enum"],"generated":true},{"anchor":"Default-Implementations","title":"Default Implementations","identifiers":["doc:\/\/com.applayr.MapLayr\/documentation\/MapLayr\/MapView\/UIGestureRecognizerDelegate-Implementations"],"generated":true}],"primaryContentSections":[{"declarations":[{"languages":["swift"],"tokens":[{"text":"@","kind":"attribute"},{"text":"MainActor","preciseIdentifier":"s:ScM","kind":"attribute"},{"text":" ","kind":"text"},{"text":"final","kind":"keyword"},{"text":" ","kind":"text"},{"text":"class","kind":"keyword"},{"text":" ","kind":"text"},{"text":"MapView","kind":"identifier"}],"platforms":["iOS"]}],"kind":"declarations"}],"metadata":{"roleHeading":"Class","symbolKind":"class","modules":[{"name":"MapLayr"}],"title":"MapView","externalID":"c:@M@MapLayrInternal@objc(cs)MapView","fragments":[{"text":"class","kind":"keyword"},{"text":" ","kind":"text"},{"text":"MapView","kind":"identifier"}],"role":"symbol","navigatorTitle":[{"text":"MapView","kind":"identifier"}]},"references":{"doc://com.applayr.MapLayr/documentation/MapLayr/MapView/focusedBuildings":{"role":"symbol","fragments":[{"text":"var","kind":"keyword"},{"text":" ","kind":"text"},{"text":"focusedBuildings","kind":"identifier"},{"text":": ","kind":"text"},{"text":"Set","preciseIdentifier":"s:Sh","kind":"typeIdentifier"},{"text":"<","kind":"text"},{"text":"Building","preciseIdentifier":"s:15MapLayrInternal8BuildingC","kind":"typeIdentifier"},{"text":">","kind":"text"}],"identifier":"doc:\/\/com.applayr.MapLayr\/documentation\/MapLayr\/MapView\/focusedBuildings","abstract":[{"type":"text","text":"The buildings that are in the camera’s area of influence."}],"kind":"symbol","type":"topic","title":"focusedBuildings","url":"\/documentation\/maplayr\/mapview\/focusedbuildings"},"doc://com.applayr.MapLayr/documentation/MapLayr/MapView/setProvider(position:orientation:animated:)":{"abstract":[{"type":"text","text":"Sets one or more of the camera state providers, optionally animating the transition."}],"role":"symbol","type":"topic","identifier":"doc:\/\/com.applayr.MapLayr\/documentation\/MapLayr\/MapView\/setProvider(position:orientation:animated:)","fragments":[{"text":"func","kind":"keyword"},{"text":" ","kind":"text"},{"text":"setProvider","kind":"identifier"},{"text":"(","kind":"text"},{"text":"position","kind":"externalParam"},{"text":": (any ","kind":"text"},{"text":"CameraPositionProvider","preciseIdentifier":"s:15MapLayrInternal22CameraPositionProviderP","kind":"typeIdentifier"},{"text":")?, ","kind":"text"},{"text":"orientation","kind":"externalParam"},{"text":": (any ","kind":"text"},{"text":"CameraOrientationProvider","preciseIdentifier":"s:15MapLayrInternal25CameraOrientationProviderP","kind":"typeIdentifier"},{"text":")?, ","kind":"text"},{"text":"animated","kind":"externalParam"},{"text":": ","kind":"text"},{"text":"Bool","preciseIdentifier":"s:Sb","kind":"typeIdentifier"},{"text":")","kind":"text"}],"kind":"symbol","title":"setProvider(position:orientation:animated:)","url":"\/documentation\/maplayr\/mapview\/setprovider(position:orientation:animated:)"},"doc://com.applayr.MapLayr/objc(pl)UIAccessibilityIdentification":{"type":"unresolvable","title":"UIKit.UIAccessibilityIdentification","identifier":"doc:\/\/com.applayr.MapLayr\/objc(pl)UIAccessibilityIdentification"},"doc://com.applayr.MapLayr/documentation/MapLayr/MapView/LightsMode-swift.enum":{"navigatorTitle":[{"text":"LightsMode","kind":"identifier"}],"url":"\/documentation\/maplayr\/mapview\/lightsmode-swift.enum","abstract":[{"text":"The possible mode of the lighting effects.","type":"text"}],"role":"symbol","type":"topic","identifier":"doc:\/\/com.applayr.MapLayr\/documentation\/MapLayr\/MapView\/LightsMode-swift.enum","kind":"symbol","title":"MapView.LightsMode","fragments":[{"text":"enum","kind":"keyword"},{"text":" ","kind":"text"},{"text":"LightsMode","kind":"identifier"}]},"doc://com.applayr.MapLayr/documentation/MapLayr/MapView/adjustedContentInset":{"abstract":[{"type":"text","text":"The actual content inset used by the map view, including the safe area when specified."}],"role":"symbol","type":"topic","identifier":"doc:\/\/com.applayr.MapLayr\/documentation\/MapLayr\/MapView\/adjustedContentInset","fragments":[{"text":"var","kind":"keyword"},{"text":" ","kind":"text"},{"text":"adjustedContentInset","kind":"identifier"},{"text":": ","kind":"text"},{"text":"UIEdgeInsets","preciseIdentifier":"c:@S@UIEdgeInsets","kind":"typeIdentifier"}],"kind":"symbol","title":"adjustedContentInset","url":"\/documentation\/maplayr\/mapview\/adjustedcontentinset"},"doc://com.applayr.MapLayr/documentation/MapLayr/MapView/mapLayers":{"fragments":[{"text":"var","kind":"keyword"},{"text":" ","kind":"text"},{"text":"mapLayers","kind":"identifier"},{"text":": [any ","kind":"text"},{"text":"MapLayer","preciseIdentifier":"s:15MapLayrInternal0A5LayerP","kind":"typeIdentifier"},{"text":"]","kind":"text"}],"kind":"symbol","title":"mapLayers","abstract":[{"type":"text","text":"The map layers which display above the map content."}],"url":"\/documentation\/maplayr\/mapview\/maplayers","type":"topic","identifier":"doc:\/\/com.applayr.MapLayr\/documentation\/MapLayr\/MapView\/mapLayers","role":"symbol"},"doc://com.applayr.MapLayr/documentation/MapLayr/MapView/colorTransformationMode-swift.property":{"title":"colorTransformationMode","identifier":"doc:\/\/com.applayr.MapLayr\/documentation\/MapLayr\/MapView\/colorTransformationMode-swift.property","fragments":[{"text":"var","kind":"keyword"},{"text":" ","kind":"text"},{"text":"colorTransformationMode","kind":"identifier"},{"text":": ","kind":"text"},{"text":"MapView","preciseIdentifier":"c:@M@MapLayrInternal@objc(cs)MapView","kind":"typeIdentifier"},{"text":".","kind":"text"},{"text":"ColorTransformationMode","preciseIdentifier":"s:15MapLayrInternal0A4ViewC23ColorTransformationModeO","kind":"typeIdentifier"}],"abstract":[{"type":"text","text":"The resolved mode used for determining what the colour transformation phase should be."}],"type":"topic","role":"symbol","kind":"symbol","url":"\/documentation\/maplayr\/mapview\/colortransformationmode-swift.property"},"doc://com.applayr.MapLayr/SH":{"type":"unresolvable","title":"Swift.Hashable","identifier":"doc:\/\/com.applayr.MapLayr\/SH"},"doc://com.applayr.MapLayr/documentation/MapLayr/MapView/lightsModeOverride":{"role":"symbol","abstract":[{"type":"text","text":"Override the lighting effects mode from the map."}],"identifier":"doc:\/\/com.applayr.MapLayr\/documentation\/MapLayr\/MapView\/lightsModeOverride","kind":"symbol","type":"topic","title":"lightsModeOverride","fragments":[{"text":"var","kind":"keyword"},{"kind":"text","text":" "},{"kind":"identifier","text":"lightsModeOverride"},{"kind":"text","text":": "},{"kind":"typeIdentifier","preciseIdentifier":"c:@M@MapLayrInternal@objc(cs)MapView","text":"MapView"},{"kind":"text","text":"."},{"kind":"typeIdentifier","preciseIdentifier":"s:15MapLayrInternal0A4ViewC10LightsModeO","text":"LightsMode"},{"kind":"text","text":"?"}],"url":"\/documentation\/maplayr\/mapview\/lightsmodeoverride"},"doc://com.applayr.MapLayr/documentation/MapLayr/MapView/moveCamera(coordinates:heading:span:insets:tilt:animated:)-9pbez":{"fragments":[{"text":"func","kind":"keyword"},{"text":" ","kind":"text"},{"text":"moveCamera","kind":"identifier"},{"text":"(","kind":"text"},{"text":"coordinates","kind":"externalParam"},{"text":": ","kind":"text"},{"text":"CLLocationCoordinate2D","preciseIdentifier":"c:@S@CLLocationCoordinate2D","kind":"typeIdentifier"},{"text":"?, ","kind":"text"},{"text":"heading","kind":"externalParam"},{"text":": ","kind":"text"},{"text":"Direction","preciseIdentifier":"s:11MapGeometry9Directiona","kind":"typeIdentifier"},{"text":"?, ","kind":"text"},{"text":"span","kind":"externalParam"},{"text":": ","kind":"text"},{"text":"Distance","preciseIdentifier":"s:11MapGeometry8Distancea","kind":"typeIdentifier"},{"text":"?, ","kind":"text"},{"text":"insets","kind":"externalParam"},{"text":": ","kind":"text"},{"text":"CGFloat","preciseIdentifier":"s:14CoreFoundation7CGFloatV","kind":"typeIdentifier"},{"text":", ","kind":"text"},{"text":"tilt","kind":"externalParam"},{"text":": ","kind":"text"},{"text":"Float","preciseIdentifier":"s:Sf","kind":"typeIdentifier"},{"text":"?, ","kind":"text"},{"text":"animated","kind":"externalParam"},{"text":": ","kind":"text"},{"text":"Bool","preciseIdentifier":"s:Sb","kind":"typeIdentifier"},{"text":")","kind":"text"}],"abstract":[{"type":"text","text":"Sets one or more of the position, heading and elevation of the camera, optionally with an animation."}],"kind":"symbol","type":"topic","role":"symbol","url":"\/documentation\/maplayr\/mapview\/movecamera(coordinates:heading:span:insets:tilt:animated:)-9pbez","identifier":"doc:\/\/com.applayr.MapLayr\/documentation\/MapLayr\/MapView\/moveCamera(coordinates:heading:span:insets:tilt:animated:)-9pbez","title":"moveCamera(coordinates:heading:span:insets:tilt:animated:)"},"doc://com.applayr.MapLayr/documentation/MapLayr/MapView/map":{"kind":"symbol","type":"topic","url":"\/documentation\/maplayr\/mapview\/map","abstract":[{"type":"text","text":"The map currently assigned to the map view."}],"role":"symbol","fragments":[{"kind":"keyword","text":"var"},{"kind":"text","text":" "},{"kind":"identifier","text":"map"},{"kind":"text","text":": "},{"kind":"typeIdentifier","text":"Map","preciseIdentifier":"s:15MapLayrInternal0A0C"},{"kind":"text","text":"?"}],"identifier":"doc:\/\/com.applayr.MapLayr\/documentation\/MapLayr\/MapView\/map","title":"map"},"doc://com.applayr.MapLayr/documentation/MapLayr/MapView/addUserLocationMarker(_:)":{"fragments":[{"text":"func","kind":"keyword"},{"text":" ","kind":"text"},{"text":"addUserLocationMarker","kind":"identifier"},{"text":"(","kind":"text"},{"text":"UserLocationMarker","preciseIdentifier":"c:@M@MapLayrInternal@objc(cs)UserLocationMarker","kind":"typeIdentifier"},{"text":")","kind":"text"}],"abstract":[{"type":"text","text":"Adds the given user location marker to the map."}],"kind":"symbol","type":"topic","role":"symbol","url":"\/documentation\/maplayr\/mapview\/adduserlocationmarker(_:)","identifier":"doc:\/\/com.applayr.MapLayr\/documentation\/MapLayr\/MapView\/addUserLocationMarker(_:)","title":"addUserLocationMarker(_:)"},"doc://com.applayr.MapLayr/documentation/MapLayr/MapView/convert(_:to:)-638ab":{"kind":"symbol","url":"\/documentation\/maplayr\/mapview\/convert(_:to:)-638ab","role":"symbol","abstract":[{"type":"text","text":"Converts some coordinates to a point in the given coordinate space."}],"fragments":[{"text":"func","kind":"keyword"},{"text":" ","kind":"text"},{"text":"convert","kind":"identifier"},{"text":"(","kind":"text"},{"text":"Coordinates","preciseIdentifier":"s:11MapGeometry11CoordinatesV","kind":"typeIdentifier"},{"text":", ","kind":"text"},{"text":"to","kind":"externalParam"},{"text":": any ","kind":"text"},{"text":"UICoordinateSpace","preciseIdentifier":"c:objc(pl)UICoordinateSpace","kind":"typeIdentifier"},{"text":") -> ","kind":"text"},{"text":"CGPoint","preciseIdentifier":"c:@S@CGPoint","kind":"typeIdentifier"},{"text":"?","kind":"text"}],"title":"convert(_:to:)","identifier":"doc:\/\/com.applayr.MapLayr\/documentation\/MapLayr\/MapView\/convert(_:to:)-638ab","type":"topic"},"doc://com.applayr.MapLayr/documentation/MapLayr/MapView":{"fragments":[{"kind":"keyword","text":"class"},{"kind":"text","text":" "},{"kind":"identifier","text":"MapView"}],"type":"topic","role":"symbol","abstract":[{"type":"text","text":"A view which displays interactive map content."}],"title":"MapView","url":"\/documentation\/maplayr\/mapview","navigatorTitle":[{"kind":"identifier","text":"MapView"}],"identifier":"doc:\/\/com.applayr.MapLayr\/documentation\/MapLayr\/MapView","kind":"symbol"},"doc://com.applayr.MapLayr/documentation/MapLayr/MapView/showLevel(_:)":{"abstract":[{"type":"text","text":"Shows the specified building level inside the map view."}],"url":"\/documentation\/maplayr\/mapview\/showlevel(_:)","fragments":[{"text":"func","kind":"keyword"},{"text":" ","kind":"text"},{"text":"showLevel","kind":"identifier"},{"text":"(","kind":"text"},{"text":"String","preciseIdentifier":"s:SS","kind":"typeIdentifier"},{"text":"?)","kind":"text"}],"type":"topic","kind":"symbol","role":"symbol","identifier":"doc:\/\/com.applayr.MapLayr\/documentation\/MapLayr\/MapView\/showLevel(_:)","title":"showLevel(_:)"},"doc://com.applayr.MapLayr/documentation/MapLayr/MapView/convert(_:from:)":{"title":"convert(_:from:)","fragments":[{"kind":"keyword","text":"func"},{"kind":"text","text":" "},{"kind":"identifier","text":"convert"},{"kind":"text","text":"("},{"kind":"typeIdentifier","preciseIdentifier":"c:@S@CGPoint","text":"CGPoint"},{"kind":"text","text":", "},{"kind":"externalParam","text":"from"},{"kind":"text","text":": any "},{"kind":"typeIdentifier","preciseIdentifier":"c:objc(pl)UICoordinateSpace","text":"UICoordinateSpace"},{"kind":"text","text":") -> "},{"kind":"typeIdentifier","preciseIdentifier":"s:11MapGeometry11CoordinatesV","text":"Coordinates"},{"text":"?","kind":"text"}],"type":"topic","kind":"symbol","identifier":"doc:\/\/com.applayr.MapLayr\/documentation\/MapLayr\/MapView\/convert(_:from:)","url":"\/documentation\/maplayr\/mapview\/convert(_:from:)","abstract":[{"text":"Converts a point in the given view to coordinates.","type":"text"}],"role":"symbol"},"doc://com.applayr.MapLayr/s28CustomDebugStringConvertibleP":{"type":"unresolvable","title":"Swift.CustomDebugStringConvertible","identifier":"doc:\/\/com.applayr.MapLayr\/s28CustomDebugStringConvertibleP"},"doc://com.applayr.MapLayr/objc(pl)UIFocusItemContainer":{"type":"unresolvable","title":"UIKit.UIFocusItemContainer","identifier":"doc:\/\/com.applayr.MapLayr\/objc(pl)UIFocusItemContainer"},"doc://com.applayr.MapLayr/documentation/MapLayr/MapView/spanRange":{"fragments":[{"text":"var","kind":"keyword"},{"text":" ","kind":"text"},{"text":"spanRange","kind":"identifier"},{"text":": ","kind":"text"},{"text":"ClosedRange","preciseIdentifier":"s:SN","kind":"typeIdentifier"},{"text":"<","kind":"text"},{"text":"Distance","preciseIdentifier":"s:11MapGeometry8Distancea","kind":"typeIdentifier"},{"text":">","kind":"text"}],"kind":"symbol","url":"\/documentation\/maplayr\/mapview\/spanrange","identifier":"doc:\/\/com.applayr.MapLayr\/documentation\/MapLayr\/MapView\/spanRange","abstract":[{"type":"text","text":"The allowable camera span range in metres."}],"title":"spanRange","type":"topic","role":"symbol"},"doc://com.applayr.MapLayr/documentation/MapLayr/MapView/mapPoint":{"title":"mapPoint","fragments":[{"text":"var","kind":"keyword"},{"text":" ","kind":"text"},{"text":"mapPoint","kind":"identifier"},{"text":": ","kind":"text"},{"text":"MapPoint","kind":"typeIdentifier","preciseIdentifier":"s:11MapGeometry0A5PointV"}],"kind":"symbol","identifier":"doc:\/\/com.applayr.MapLayr\/documentation\/MapLayr\/MapView\/mapPoint","abstract":[{"text":"Returns the camera’s current map point.","type":"text"}],"url":"\/documentation\/maplayr\/mapview\/mappoint","role":"symbol","type":"topic"},"doc://com.applayr.MapLayr/objc(pl)NSCoding":{"type":"unresolvable","title":"Foundation.NSCoding","identifier":"doc:\/\/com.applayr.MapLayr\/objc(pl)NSCoding"},"doc://com.applayr.MapLayr/objc(pl)UIAppearanceContainer":{"type":"unresolvable","title":"UIKit.UIAppearanceContainer","identifier":"doc:\/\/com.applayr.MapLayr\/objc(pl)UIAppearanceContainer"},"doc://com.applayr.MapLayr/documentation/MapLayr/MapView/init(frame:)":{"fragments":[{"text":"init","kind":"identifier"},{"text":"(","kind":"text"},{"text":"frame","kind":"externalParam"},{"text":": ","kind":"text"},{"text":"CGRect","preciseIdentifier":"c:@S@CGRect","kind":"typeIdentifier"},{"text":")","kind":"text"}],"type":"topic","identifier":"doc:\/\/com.applayr.MapLayr\/documentation\/MapLayr\/MapView\/init(frame:)","kind":"symbol","abstract":[],"role":"symbol","title":"init(frame:)","url":"\/documentation\/maplayr\/mapview\/init(frame:)"},"doc://com.applayr.MapLayr/documentation/MapLayr/MapView/isTransitioningLayers":{"identifier":"doc:\/\/com.applayr.MapLayr\/documentation\/MapLayr\/MapView\/isTransitioningLayers","type":"topic","url":"\/documentation\/maplayr\/mapview\/istransitioninglayers","title":"isTransitioningLayers","fragments":[{"text":"var","kind":"keyword"},{"text":" ","kind":"text"},{"text":"isTransitioningLayers","kind":"identifier"},{"text":": ","kind":"text"},{"text":"Bool","preciseIdentifier":"s:Sb","kind":"typeIdentifier"}],"abstract":[{"type":"text","text":"Whether layer changes are currently animating."}],"kind":"symbol","role":"symbol"},"doc://com.applayr.MapLayr/documentation/MapLayr/MapView/mapSpanRange":{"type":"topic","identifier":"doc:\/\/com.applayr.MapLayr\/documentation\/MapLayr\/MapView\/mapSpanRange","role":"symbol","fragments":[{"text":"var","kind":"keyword"},{"text":" ","kind":"text"},{"text":"mapSpanRange","kind":"identifier"},{"text":": ","kind":"text"},{"text":"ClosedRange","preciseIdentifier":"s:SN","kind":"typeIdentifier"},{"text":"<","kind":"text"},{"text":"Double","preciseIdentifier":"s:Sd","kind":"typeIdentifier"},{"text":">","kind":"text"}],"title":"mapSpanRange","url":"\/documentation\/maplayr\/mapview\/mapspanrange","abstract":[{"type":"text","text":"The allowable camera span range in map units."}],"kind":"symbol"},"doc://com.applayr.MapLayr/documentation/MapLayr/MapView/scale(at:)-321bl":{"url":"\/documentation\/maplayr\/mapview\/scale(at:)-321bl","role":"symbol","title":"scale(at:)","fragments":[{"text":"func","kind":"keyword"},{"text":" ","kind":"text"},{"text":"scale","kind":"identifier"},{"text":"(","kind":"text"},{"text":"at","kind":"externalParam"},{"text":": ","kind":"text"},{"text":"Coordinates","preciseIdentifier":"s:11MapGeometry11CoordinatesV","kind":"typeIdentifier"},{"text":") -> ","kind":"text"},{"text":"CGFloat","preciseIdentifier":"s:14CoreFoundation7CGFloatV","kind":"typeIdentifier"},{"text":"?","kind":"text"}],"identifier":"doc:\/\/com.applayr.MapLayr\/documentation\/MapLayr\/MapView\/scale(at:)-321bl","abstract":[{"type":"text","text":"Returns the UIKit scale (in points per metre) for the given coordinates."}],"type":"topic","kind":"symbol"},"doc://com.applayr.MapLayr/documentation/MapLayr/MapView/convert(_:to:)-1wyv9":{"type":"topic","fragments":[{"text":"func","kind":"keyword"},{"text":" ","kind":"text"},{"text":"convert","kind":"identifier"},{"text":"(","kind":"text"},{"text":"MapPoint","preciseIdentifier":"s:11MapGeometry0A5PointV","kind":"typeIdentifier"},{"text":", ","kind":"text"},{"text":"to","kind":"externalParam"},{"text":": any ","kind":"text"},{"text":"UICoordinateSpace","preciseIdentifier":"c:objc(pl)UICoordinateSpace","kind":"typeIdentifier"},{"text":") -> ","kind":"text"},{"text":"CGPoint","preciseIdentifier":"c:@S@CGPoint","kind":"typeIdentifier"},{"text":"?","kind":"text"}],"identifier":"doc:\/\/com.applayr.MapLayr\/documentation\/MapLayr\/MapView\/convert(_:to:)-1wyv9","title":"convert(_:to:)","role":"symbol","kind":"symbol","abstract":[{"type":"text","text":"Converts a map point to a UIKit point in the given coordinate space."}],"url":"\/documentation\/maplayr\/mapview\/convert(_:to:)-1wyv9"},"doc://com.applayr.MapLayr/documentation/MapLayr/MapView/removeMapLayer(_:)":{"kind":"symbol","abstract":[{"type":"text","text":"Removes the specified map layer."}],"type":"topic","title":"removeMapLayer(_:)","role":"symbol","fragments":[{"text":"func","kind":"keyword"},{"text":" ","kind":"text"},{"text":"removeMapLayer","kind":"identifier"},{"text":"(any ","kind":"text"},{"text":"MapLayer","preciseIdentifier":"s:15MapLayrInternal0A5LayerP","kind":"typeIdentifier"},{"text":")","kind":"text"}],"url":"\/documentation\/maplayr\/mapview\/removemaplayer(_:)","identifier":"doc:\/\/com.applayr.MapLayr\/documentation\/MapLayr\/MapView\/removeMapLayer(_:)"},"doc://com.applayr.MapLayr/documentation/MapLayr/MapView/lightsMode-swift.property":{"abstract":[{"type":"text","text":"The resolved lighting effects mode."}],"title":"lightsMode","role":"symbol","url":"\/documentation\/maplayr\/mapview\/lightsmode-swift.property","type":"topic","fragments":[{"text":"var","kind":"keyword"},{"text":" ","kind":"text"},{"text":"lightsMode","kind":"identifier"},{"text":": ","kind":"text"},{"text":"MapView","preciseIdentifier":"c:@M@MapLayrInternal@objc(cs)MapView","kind":"typeIdentifier"},{"text":".","kind":"text"},{"text":"LightsMode","preciseIdentifier":"s:15MapLayrInternal0A4ViewC10LightsModeO","kind":"typeIdentifier"}],"kind":"symbol","identifier":"doc:\/\/com.applayr.MapLayr\/documentation\/MapLayr\/MapView\/lightsMode-swift.property"},"doc://com.applayr.MapLayr/documentation/MapLayr/MapView/orientationProvider":{"abstract":[{"type":"text","text":"An orientation provider which can optionally provide the camera’s orientation."}],"kind":"symbol","title":"orientationProvider","role":"symbol","type":"topic","fragments":[{"text":"var","kind":"keyword"},{"text":" ","kind":"text"},{"text":"orientationProvider","kind":"identifier"},{"text":": (any ","kind":"text"},{"text":"CameraOrientationProvider","preciseIdentifier":"s:15MapLayrInternal25CameraOrientationProviderP","kind":"typeIdentifier"},{"text":")?","kind":"text"}],"identifier":"doc:\/\/com.applayr.MapLayr\/documentation\/MapLayr\/MapView\/orientationProvider","url":"\/documentation\/maplayr\/mapview\/orientationprovider"},"doc://com.applayr.MapLayr/documentation/MapLayr":{"kind":"symbol","url":"\/documentation\/maplayr","type":"topic","title":"MapLayr","role":"collection","identifier":"doc:\/\/com.applayr.MapLayr\/documentation\/MapLayr","abstract":[{"type":"text","text":"High performance map view for venue-specific maps."}]},"doc://com.applayr.MapLayr/documentation/MapLayr/MapView/tilt":{"title":"tilt","type":"topic","identifier":"doc:\/\/com.applayr.MapLayr\/documentation\/MapLayr\/MapView\/tilt","url":"\/documentation\/maplayr\/mapview\/tilt","role":"symbol","fragments":[{"text":"var","kind":"keyword"},{"text":" ","kind":"text"},{"text":"tilt","kind":"identifier"},{"text":": ","kind":"text"},{"text":"Double","preciseIdentifier":"s:Sd","kind":"typeIdentifier"}],"kind":"symbol","abstract":[{"type":"text","text":"The camera’s current tilt in radians."}]},"doc://com.applayr.MapLayr/objc(pl)UIDynamicItem":{"type":"unresolvable","title":"UIKit.UIDynamicItem","identifier":"doc:\/\/com.applayr.MapLayr\/objc(pl)UIDynamicItem"},"doc://com.applayr.MapLayr/objc(pl)UIFocusEnvironment":{"type":"unresolvable","title":"UIKit.UIFocusEnvironment","identifier":"doc:\/\/com.applayr.MapLayr\/objc(pl)UIFocusEnvironment"},"doc://com.applayr.MapLayr/documentation/MapLayr/MapView/convert(_:to:)-br3v":{"type":"topic","title":"convert(_:to:)","url":"\/documentation\/maplayr\/mapview\/convert(_:to:)-br3v","kind":"symbol","fragments":[{"text":"func","kind":"keyword"},{"text":" ","kind":"text"},{"text":"convert","kind":"identifier"},{"text":"(","kind":"text"},{"text":"CLLocationCoordinate2D","preciseIdentifier":"c:@S@CLLocationCoordinate2D","kind":"typeIdentifier"},{"text":", ","kind":"text"},{"text":"to","kind":"externalParam"},{"text":": any ","kind":"text"},{"text":"UICoordinateSpace","preciseIdentifier":"c:objc(pl)UICoordinateSpace","kind":"typeIdentifier"},{"text":") -> ","kind":"text"},{"text":"CGPoint","preciseIdentifier":"c:@S@CGPoint","kind":"typeIdentifier"},{"text":"?","kind":"text"}],"abstract":[{"type":"text","text":"Converts some coordinates to a point in the given coordinate space."}],"role":"symbol","identifier":"doc:\/\/com.applayr.MapLayr\/documentation\/MapLayr\/MapView\/convert(_:to:)-br3v"},"doc://com.applayr.MapLayr/documentation/MapLayr/MapView/traitCollectionDidChange(_:)":{"title":"traitCollectionDidChange(_:)","type":"topic","identifier":"doc:\/\/com.applayr.MapLayr\/documentation\/MapLayr\/MapView\/traitCollectionDidChange(_:)","url":"\/documentation\/maplayr\/mapview\/traitcollectiondidchange(_:)","role":"symbol","fragments":[{"text":"func","kind":"keyword"},{"text":" ","kind":"text"},{"text":"traitCollectionDidChange","kind":"identifier"},{"text":"(","kind":"text"},{"text":"UITraitCollection","preciseIdentifier":"c:objc(cs)UITraitCollection","kind":"typeIdentifier"},{"text":"?)","kind":"text"}],"kind":"symbol","abstract":[]},"doc://com.applayr.MapLayr/objc(pl)UIResponderStandardEditActions":{"type":"unresolvable","title":"UIKit.UIResponderStandardEditActions","identifier":"doc:\/\/com.applayr.MapLayr\/objc(pl)UIResponderStandardEditActions"},"doc://com.applayr.MapLayr/documentation/MapLayr/MapView/mapSpan":{"role":"symbol","identifier":"doc:\/\/com.applayr.MapLayr\/documentation\/MapLayr\/MapView\/mapSpan","abstract":[{"type":"text","text":"The current span of the camera in map units."}],"fragments":[{"text":"var","kind":"keyword"},{"text":" ","kind":"text"},{"text":"mapSpan","kind":"identifier"},{"text":": ","kind":"text"},{"text":"Double","preciseIdentifier":"s:Sd","kind":"typeIdentifier"}],"kind":"symbol","type":"topic","url":"\/documentation\/maplayr\/mapview\/mapspan","title":"mapSpan"},"doc://com.applayr.MapLayr/documentation/MapLayr/MapView/delegate":{"url":"\/documentation\/maplayr\/mapview\/delegate","identifier":"doc:\/\/com.applayr.MapLayr\/documentation\/MapLayr\/MapView\/delegate","fragments":[{"text":"var","kind":"keyword"},{"text":" ","kind":"text"},{"text":"delegate","kind":"identifier"},{"text":": (any ","kind":"text"},{"text":"MapViewDelegate","preciseIdentifier":"s:15MapLayrInternal0A12ViewDelegateP","kind":"typeIdentifier"},{"text":")?","kind":"text"}],"kind":"symbol","title":"delegate","abstract":[{"type":"text","text":"The map view’s delegate."}],"role":"symbol","type":"topic"},"doc://com.applayr.MapLayr/5UIKit23UITraitChangeObservableP":{"type":"unresolvable","title":"UIKit.UITraitChangeObservable","identifier":"doc:\/\/com.applayr.MapLayr\/5UIKit23UITraitChangeObservableP"},"doc://com.applayr.MapLayr/documentation/MapLayr/MapView/UIGestureRecognizerDelegate-Implementations":{"abstract":[],"url":"\/documentation\/maplayr\/mapview\/uigesturerecognizerdelegate-implementations","identifier":"doc:\/\/com.applayr.MapLayr\/documentation\/MapLayr\/MapView\/UIGestureRecognizerDelegate-Implementations","title":"UIGestureRecognizerDelegate Implementations","type":"topic","kind":"article","role":"collectionGroup"},"doc://com.applayr.MapLayr/documentation/MapLayr/MapView/convert(_:to:)-93zcu":{"fragments":[{"text":"func","kind":"keyword"},{"text":" ","kind":"text"},{"text":"convert","kind":"identifier"},{"text":"(","kind":"text"},{"text":"MultilevelMapPoint","preciseIdentifier":"s:15MapLayrInternal010MultilevelA5PointV","kind":"typeIdentifier"},{"text":", ","kind":"text"},{"text":"to","kind":"externalParam"},{"text":": any ","kind":"text"},{"text":"UICoordinateSpace","preciseIdentifier":"c:objc(pl)UICoordinateSpace","kind":"typeIdentifier"},{"text":") -> ","kind":"text"},{"text":"CGPoint","preciseIdentifier":"c:@S@CGPoint","kind":"typeIdentifier"},{"text":"?","kind":"text"}],"abstract":[{"type":"text","text":"Converts a map point to a UIKit point in the given coordinate space."}],"url":"\/documentation\/maplayr\/mapview\/convert(_:to:)-93zcu","identifier":"doc:\/\/com.applayr.MapLayr\/documentation\/MapLayr\/MapView\/convert(_:to:)-93zcu","title":"convert(_:to:)","type":"topic","kind":"symbol","role":"symbol"},"doc://com.applayr.MapLayr/documentation/MapLayr/MapView/layoutSubviews()":{"identifier":"doc:\/\/com.applayr.MapLayr\/documentation\/MapLayr\/MapView\/layoutSubviews()","kind":"symbol","title":"layoutSubviews()","type":"topic","url":"\/documentation\/maplayr\/mapview\/layoutsubviews()","abstract":[],"role":"symbol","fragments":[{"text":"func","kind":"keyword"},{"text":" ","kind":"text"},{"text":"layoutSubviews","kind":"identifier"},{"text":"()","kind":"text"}]},"doc://com.applayr.MapLayr/documentation/MapLayr/MapView/moveCamera(coordinates:heading:span:insets:tilt:animated:)-942rx":{"fragments":[{"text":"func","kind":"keyword"},{"text":" ","kind":"text"},{"text":"moveCamera","kind":"identifier"},{"text":"(","kind":"text"},{"text":"coordinates","kind":"externalParam"},{"text":": ","kind":"text"},{"text":"Coordinates","preciseIdentifier":"s:11MapGeometry11CoordinatesV","kind":"typeIdentifier"},{"text":"?, ","kind":"text"},{"text":"heading","kind":"externalParam"},{"text":": ","kind":"text"},{"text":"CLLocationDirection","preciseIdentifier":"c:@T@CLLocationDirection","kind":"typeIdentifier"},{"text":"?, ","kind":"text"},{"text":"span","kind":"externalParam"},{"text":": ","kind":"text"},{"text":"CLLocationDistance","preciseIdentifier":"c:@T@CLLocationDistance","kind":"typeIdentifier"},{"text":"?, ","kind":"text"},{"text":"insets","kind":"externalParam"},{"text":": ","kind":"text"},{"text":"CGFloat","preciseIdentifier":"s:14CoreFoundation7CGFloatV","kind":"typeIdentifier"},{"text":", ","kind":"text"},{"text":"tilt","kind":"externalParam"},{"text":": ","kind":"text"},{"text":"Float","preciseIdentifier":"s:Sf","kind":"typeIdentifier"},{"text":"?, ","kind":"text"},{"text":"animated","kind":"externalParam"},{"text":": ","kind":"text"},{"text":"Bool","preciseIdentifier":"s:Sb","kind":"typeIdentifier"},{"text":")","kind":"text"}],"title":"moveCamera(coordinates:heading:span:insets:tilt:animated:)","kind":"symbol","identifier":"doc:\/\/com.applayr.MapLayr\/documentation\/MapLayr\/MapView\/moveCamera(coordinates:heading:span:insets:tilt:animated:)-942rx","type":"topic","abstract":[{"type":"text","text":"Sets one or more of the position, heading and elevation of the camera, optionally with an animation."}],"url":"\/documentation\/maplayr\/mapview\/movecamera(coordinates:heading:span:insets:tilt:animated:)-942rx","role":"symbol"},"doc://com.applayr.MapLayr/documentation/MapLayr/MapView/positionProvider":{"fragments":[{"text":"var","kind":"keyword"},{"text":" ","kind":"text"},{"text":"positionProvider","kind":"identifier"},{"text":": (any ","kind":"text"},{"text":"CameraPositionProvider","preciseIdentifier":"s:15MapLayrInternal22CameraPositionProviderP","kind":"typeIdentifier"},{"text":")?","kind":"text"}],"title":"positionProvider","kind":"symbol","identifier":"doc:\/\/com.applayr.MapLayr\/documentation\/MapLayr\/MapView\/positionProvider","type":"topic","abstract":[{"type":"text","text":"A position provider which can optionally provide the camera’s position."}],"url":"\/documentation\/maplayr\/mapview\/positionprovider","role":"symbol"},"doc://com.applayr.MapLayr/s7CVarArgP":{"type":"unresolvable","title":"Swift.CVarArg","identifier":"doc:\/\/com.applayr.MapLayr\/s7CVarArgP"},"doc://com.applayr.MapLayr/documentation/MapLayr/MapView/includeSafeAreaInAdjustedContentInset":{"abstract":[{"type":"text","text":"Whether the derived content inset includes the safe area."}],"fragments":[{"text":"var","kind":"keyword"},{"text":" ","kind":"text"},{"text":"includeSafeAreaInAdjustedContentInset","kind":"identifier"},{"text":": ","kind":"text"},{"text":"Bool","preciseIdentifier":"s:Sb","kind":"typeIdentifier"}],"role":"symbol","title":"includeSafeAreaInAdjustedContentInset","url":"\/documentation\/maplayr\/mapview\/includesafeareainadjustedcontentinset","kind":"symbol","type":"topic","identifier":"doc:\/\/com.applayr.MapLayr\/documentation\/MapLayr\/MapView\/includeSafeAreaInAdjustedContentInset"},"doc://com.applayr.MapLayr/s8CopyableP":{"type":"unresolvable","title":"Swift.Copyable","identifier":"doc:\/\/com.applayr.MapLayr\/s8CopyableP"},"doc://com.applayr.MapLayr/objc(pl)UIActivityItemsConfigurationProviding":{"type":"unresolvable","title":"UIKit.UIActivityItemsConfigurationProviding","identifier":"doc:\/\/com.applayr.MapLayr\/objc(pl)UIActivityItemsConfigurationProviding"},"doc://com.applayr.MapLayr/s8SendableP":{"type":"unresolvable","title":"Swift.Sendable","identifier":"doc:\/\/com.applayr.MapLayr\/s8SendableP"},"doc://com.applayr.MapLayr/objc(pl)UIAppearance":{"type":"unresolvable","title":"UIKit.UIAppearance","identifier":"doc:\/\/com.applayr.MapLayr\/objc(pl)UIAppearance"},"doc://com.applayr.MapLayr/documentation/MapLayr/MapView/angle(at:heading:)-9o619":{"kind":"symbol","abstract":[{"type":"text","text":"Returns the angle of the given heading at the given coordinate in radians."}],"fragments":[{"text":"func","kind":"keyword"},{"text":" ","kind":"text"},{"text":"angle","kind":"identifier"},{"text":"(","kind":"text"},{"text":"at","kind":"externalParam"},{"text":": ","kind":"text"},{"text":"CLLocationCoordinate2D","preciseIdentifier":"c:@S@CLLocationCoordinate2D","kind":"typeIdentifier"},{"text":", ","kind":"text"},{"text":"heading","kind":"externalParam"},{"text":": ","kind":"text"},{"text":"CLLocationDirection","preciseIdentifier":"c:@T@CLLocationDirection","kind":"typeIdentifier"},{"text":") -> ","kind":"text"},{"text":"CGFloat","preciseIdentifier":"s:14CoreFoundation7CGFloatV","kind":"typeIdentifier"},{"text":"?","kind":"text"}],"identifier":"doc:\/\/com.applayr.MapLayr\/documentation\/MapLayr\/MapView\/angle(at:heading:)-9o619","role":"symbol","url":"\/documentation\/maplayr\/mapview\/angle(at:heading:)-9o619","title":"angle(at:heading:)","type":"topic"},"doc://com.applayr.MapLayr/documentation/MapLayr/MapViewDelegate":{"identifier":"doc:\/\/com.applayr.MapLayr\/documentation\/MapLayr\/MapViewDelegate","type":"topic","abstract":[{"text":"A protocol that defines methods for receiving map view updates and events.","type":"text"}],"role":"symbol","title":"MapViewDelegate","fragments":[{"text":"protocol","kind":"keyword"},{"text":" ","kind":"text"},{"text":"MapViewDelegate","kind":"identifier"}],"navigatorTitle":[{"text":"MapViewDelegate","kind":"identifier"}],"url":"\/documentation\/maplayr\/mapviewdelegate","kind":"symbol"},"doc://com.applayr.MapLayr/documentation/MapLayr/MapView/convert(_:to:)-18ee4":{"kind":"symbol","abstract":[{"type":"text","text":"Converts some coordinates to a point in the given coordinate space."}],"fragments":[{"text":"func","kind":"keyword"},{"text":" ","kind":"text"},{"text":"convert","kind":"identifier"},{"text":"(","kind":"text"},{"text":"MultilevelCoordinates","preciseIdentifier":"s:15MapLayrInternal21MultilevelCoordinatesV","kind":"typeIdentifier"},{"text":", ","kind":"text"},{"text":"to","kind":"externalParam"},{"text":": any ","kind":"text"},{"text":"UICoordinateSpace","preciseIdentifier":"c:objc(pl)UICoordinateSpace","kind":"typeIdentifier"},{"text":") -> ","kind":"text"},{"text":"CGPoint","preciseIdentifier":"c:@S@CGPoint","kind":"typeIdentifier"},{"text":"?","kind":"text"}],"identifier":"doc:\/\/com.applayr.MapLayr\/documentation\/MapLayr\/MapView\/convert(_:to:)-18ee4","role":"symbol","url":"\/documentation\/maplayr\/mapview\/convert(_:to:)-18ee4","title":"convert(_:to:)","type":"topic"},"doc://com.applayr.MapLayr/objc(cs)UIView":{"type":"unresolvable","title":"UIKit.UIView","identifier":"doc:\/\/com.applayr.MapLayr\/objc(cs)UIView"},"doc://com.applayr.MapLayr/documentation/MapLayr/MapView/removeMapLayer(at:)":{"fragments":[{"text":"func","kind":"keyword"},{"text":" ","kind":"text"},{"text":"removeMapLayer","kind":"identifier"},{"text":"(","kind":"text"},{"text":"at","kind":"externalParam"},{"text":": ","kind":"text"},{"text":"Int","preciseIdentifier":"s:Si","kind":"typeIdentifier"},{"text":") -> any ","kind":"text"},{"text":"MapLayer","preciseIdentifier":"s:15MapLayrInternal0A5LayerP","kind":"typeIdentifier"}],"kind":"symbol","abstract":[{"type":"text","text":"Removes and returns the map layer at the given index."}],"url":"\/documentation\/maplayr\/mapview\/removemaplayer(at:)","identifier":"doc:\/\/com.applayr.MapLayr\/documentation\/MapLayr\/MapView\/removeMapLayer(at:)","type":"topic","title":"removeMapLayer(at:)","role":"symbol"},"doc://com.applayr.MapLayr/documentation/MapLayr/MapView/additionalContentInset":{"url":"\/documentation\/maplayr\/mapview\/additionalcontentinset","abstract":[{"text":"Optional additional content inset applied to the map view.","type":"text"}],"title":"additionalContentInset","identifier":"doc:\/\/com.applayr.MapLayr\/documentation\/MapLayr\/MapView\/additionalContentInset","kind":"symbol","role":"symbol","fragments":[{"text":"var","kind":"keyword"},{"text":" ","kind":"text"},{"text":"additionalContentInset","kind":"identifier"},{"text":": ","kind":"text"},{"text":"UIEdgeInsets","kind":"typeIdentifier","preciseIdentifier":"c:@S@UIEdgeInsets"}],"type":"topic"},"doc://com.applayr.MapLayr/objc(pl)UIFocusItem":{"type":"unresolvable","title":"UIKit.UIFocusItem","identifier":"doc:\/\/com.applayr.MapLayr\/objc(pl)UIFocusItem"},"doc://com.applayr.MapLayr/objc(pl)UITraitEnvironment":{"type":"unresolvable","title":"UIKit.UITraitEnvironment","identifier":"doc:\/\/com.applayr.MapLayr\/objc(pl)UITraitEnvironment"},"doc://com.applayr.MapLayr/documentation/MapLayr/MapView/removeUserLocationMarker(_:)":{"type":"topic","identifier":"doc:\/\/com.applayr.MapLayr\/documentation\/MapLayr\/MapView\/removeUserLocationMarker(_:)","role":"symbol","abstract":[{"type":"text","text":"Removes the given user location marker from the map."}],"url":"\/documentation\/maplayr\/mapview\/removeuserlocationmarker(_:)","kind":"symbol","title":"removeUserLocationMarker(_:)","fragments":[{"text":"func","kind":"keyword"},{"text":" ","kind":"text"},{"text":"removeUserLocationMarker","kind":"identifier"},{"text":"(","kind":"text"},{"text":"UserLocationMarker","kind":"typeIdentifier","preciseIdentifier":"c:@M@MapLayrInternal@objc(cs)UserLocationMarker"},{"text":")","kind":"text"}]},"doc://com.applayr.MapLayr/documentation/MapLayr/MapView/scale(at:)-7ucc8":{"fragments":[{"text":"func","kind":"keyword"},{"text":" ","kind":"text"},{"text":"scale","kind":"identifier"},{"text":"(","kind":"text"},{"text":"at","kind":"externalParam"},{"text":": ","kind":"text"},{"text":"CLLocationCoordinate2D","kind":"typeIdentifier","preciseIdentifier":"c:@S@CLLocationCoordinate2D"},{"text":") -> ","kind":"text"},{"text":"CGFloat","kind":"typeIdentifier","preciseIdentifier":"s:14CoreFoundation7CGFloatV"},{"text":"?","kind":"text"}],"title":"scale(at:)","url":"\/documentation\/maplayr\/mapview\/scale(at:)-7ucc8","kind":"symbol","type":"topic","abstract":[{"text":"Returns the UIKit scale (in points per metre) for the given coordinates.","type":"text"}],"role":"symbol","identifier":"doc:\/\/com.applayr.MapLayr\/documentation\/MapLayr\/MapView\/scale(at:)-7ucc8"},"doc://com.applayr.MapLayr/documentation/MapLayr/MapView/colorTransformationPhase":{"abstract":[{"type":"text","text":"The current colour transformation phase."}],"fragments":[{"text":"var","kind":"keyword"},{"text":" ","kind":"text"},{"text":"colorTransformationPhase","kind":"identifier"},{"text":": ","kind":"text"},{"text":"Float","kind":"typeIdentifier","preciseIdentifier":"s:Sf"}],"kind":"symbol","type":"topic","title":"colorTransformationPhase","role":"symbol","url":"\/documentation\/maplayr\/mapview\/colortransformationphase","identifier":"doc:\/\/com.applayr.MapLayr\/documentation\/MapLayr\/MapView\/colorTransformationPhase"},"doc://com.applayr.MapLayr/documentation/MapLayr/MapView/colorTransformationModeOverride":{"type":"topic","url":"\/documentation\/maplayr\/mapview\/colortransformationmodeoverride","abstract":[{"text":"Override the colour transformation mode specified in the map.","type":"text"}],"title":"colorTransformationModeOverride","kind":"symbol","identifier":"doc:\/\/com.applayr.MapLayr\/documentation\/MapLayr\/MapView\/colorTransformationModeOverride","fragments":[{"text":"var","kind":"keyword"},{"text":" ","kind":"text"},{"text":"colorTransformationModeOverride","kind":"identifier"},{"text":": ","kind":"text"},{"text":"MapView","kind":"typeIdentifier","preciseIdentifier":"c:@M@MapLayrInternal@objc(cs)MapView"},{"text":".","kind":"text"},{"text":"ColorTransformationMode","kind":"typeIdentifier","preciseIdentifier":"s:15MapLayrInternal0A4ViewC23ColorTransformationModeO"},{"text":"?","kind":"text"}],"role":"symbol"},"doc://com.applayr.MapLayr/objc(pl)UIGestureRecognizerDelegate":{"type":"unresolvable","identifier":"doc:\/\/com.applayr.MapLayr\/objc(pl)UIGestureRecognizerDelegate","title":"UIKit.UIGestureRecognizerDelegate"},"doc://com.applayr.MapLayr/documentation/MapLayr/MapView/addMapLayer(_:)":{"identifier":"doc:\/\/com.applayr.MapLayr\/documentation\/MapLayr\/MapView\/addMapLayer(_:)","title":"addMapLayer(_:)","fragments":[{"text":"func","kind":"keyword"},{"text":" ","kind":"text"},{"text":"addMapLayer","kind":"identifier"},{"text":"(any ","kind":"text"},{"text":"MapLayer","kind":"typeIdentifier","preciseIdentifier":"s:15MapLayrInternal0A5LayerP"},{"text":")","kind":"text"}],"abstract":[{"type":"text","text":"Adds the specified map layer."}],"type":"topic","role":"symbol","url":"\/documentation\/maplayr\/mapview\/addmaplayer(_:)","kind":"symbol"},"doc://com.applayr.MapLayr/objc(pl)UIUserActivityRestoring":{"type":"unresolvable","identifier":"doc:\/\/com.applayr.MapLayr\/objc(pl)UIUserActivityRestoring","title":"UIKit.UIUserActivityRestoring"},"doc://com.applayr.MapLayr/documentation/MapLayr/MapView/heading":{"role":"symbol","abstract":[{"type":"text","text":"The camera’s current heading in degrees relative to North."}],"fragments":[{"text":"var","kind":"keyword"},{"text":" ","kind":"text"},{"text":"heading","kind":"identifier"},{"text":": ","kind":"text"},{"text":"Direction","kind":"typeIdentifier","preciseIdentifier":"s:11MapGeometry9Directiona"}],"identifier":"doc:\/\/com.applayr.MapLayr\/documentation\/MapLayr\/MapView\/heading","title":"heading","url":"\/documentation\/maplayr\/mapview\/heading","type":"topic","kind":"symbol"},"doc://com.applayr.MapLayr/documentation/MapLayr/MapView/clearAuxiliaryLayers()":{"title":"clearAuxiliaryLayers()","url":"\/documentation\/maplayr\/mapview\/clearauxiliarylayers()","type":"topic","fragments":[{"kind":"keyword","text":"func"},{"kind":"text","text":" "},{"kind":"identifier","text":"clearAuxiliaryLayers"},{"kind":"text","text":"()"}],"kind":"symbol","abstract":[{"text":"Removes any auxiliary layers being displayed.","type":"text"}],"role":"symbol","identifier":"doc:\/\/com.applayr.MapLayr\/documentation\/MapLayr\/MapView\/clearAuxiliaryLayers()"},"doc://com.applayr.MapLayr/objc(pl)NSObject":{"type":"unresolvable","identifier":"doc:\/\/com.applayr.MapLayr\/objc(pl)NSObject","title":"ObjectiveC.NSObjectProtocol"},"doc://com.applayr.MapLayr/objc(pl)UIPopoverPresentationControllerSourceItem":{"identifier":"doc:\/\/com.applayr.MapLayr\/objc(pl)UIPopoverPresentationControllerSourceItem","title":"UIKit.UIPopoverPresentationControllerSourceItem","type":"unresolvable"},"doc://com.applayr.MapLayr/objc(pl)UICoordinateSpace":{"type":"unresolvable","identifier":"doc:\/\/com.applayr.MapLayr\/objc(pl)UICoordinateSpace","title":"UIKit.UICoordinateSpace"},"doc://com.applayr.MapLayr/documentation/MapLayr/MapView/shapes":{"role":"symbol","title":"shapes","type":"topic","abstract":[{"type":"text","text":"Shapes which are drawn on the map."}],"identifier":"doc:\/\/com.applayr.MapLayr\/documentation\/MapLayr\/MapView\/shapes","url":"\/documentation\/maplayr\/mapview\/shapes","kind":"symbol","fragments":[{"text":"var","kind":"keyword"},{"text":" ","kind":"text"},{"text":"shapes","kind":"identifier"},{"text":": [","kind":"text"},{"preciseIdentifier":"s:15MapLayrInternal5ShapeC","text":"Shape","kind":"typeIdentifier"},{"text":"]","kind":"text"}]},"doc://com.applayr.MapLayr/s23CustomStringConvertibleP":{"type":"unresolvable","identifier":"doc:\/\/com.applayr.MapLayr\/s23CustomStringConvertibleP","title":"Swift.CustomStringConvertible"},"doc://com.applayr.MapLayr/documentation/MapLayr/Map":{"kind":"symbol","fragments":[{"kind":"keyword","text":"class"},{"kind":"text","text":" "},{"kind":"identifier","text":"Map"}],"navigatorTitle":[{"kind":"identifier","text":"Map"}],"identifier":"doc:\/\/com.applayr.MapLayr\/documentation\/MapLayr\/Map","role":"symbol","abstract":[{"text":"An updatable map.","type":"text"}],"url":"\/documentation\/maplayr\/map","title":"Map","type":"topic"},"doc://com.applayr.MapLayr/objc(pl)UIPasteConfigurationSupporting":{"identifier":"doc:\/\/com.applayr.MapLayr\/objc(pl)UIPasteConfigurationSupporting","title":"UIKit.UIPasteConfigurationSupporting","type":"unresolvable"},"doc://com.applayr.MapLayr/documentation/MapLayr/MapView/ColorTransformationMode-swift.enum":{"kind":"symbol","title":"MapView.ColorTransformationMode","identifier":"doc:\/\/com.applayr.MapLayr\/documentation\/MapLayr\/MapView\/ColorTransformationMode-swift.enum","type":"topic","url":"\/documentation\/maplayr\/mapview\/colortransformationmode-swift.enum","role":"symbol","fragments":[{"text":"enum","kind":"keyword"},{"text":" ","kind":"text"},{"text":"ColorTransformationMode","kind":"identifier"}],"navigatorTitle":[{"text":"ColorTransformationMode","kind":"identifier"}],"abstract":[{"text":"The possible modes for determining the colour transformation phase.","type":"text"}]},"doc://com.applayr.MapLayr/SQ":{"identifier":"doc:\/\/com.applayr.MapLayr\/SQ","title":"Swift.Equatable","type":"unresolvable"},"doc://com.applayr.MapLayr/documentation/MapLayr/MapView/angle(at:heading:)-3rwxm":{"title":"angle(at:heading:)","kind":"symbol","fragments":[{"text":"func","kind":"keyword"},{"text":" ","kind":"text"},{"text":"angle","kind":"identifier"},{"text":"(","kind":"text"},{"text":"at","kind":"externalParam"},{"text":": ","kind":"text"},{"text":"Coordinates","kind":"typeIdentifier","preciseIdentifier":"s:11MapGeometry11CoordinatesV"},{"text":", ","kind":"text"},{"text":"heading","kind":"externalParam"},{"text":": ","kind":"text"},{"text":"Direction","kind":"typeIdentifier","preciseIdentifier":"s:11MapGeometry9Directiona"},{"text":") -> ","kind":"text"},{"text":"CGFloat","kind":"typeIdentifier","preciseIdentifier":"s:14CoreFoundation7CGFloatV"},{"text":"?","kind":"text"}],"role":"symbol","url":"\/documentation\/maplayr\/mapview\/angle(at:heading:)-3rwxm","abstract":[{"type":"text","text":"Returns the angle of the given heading at the given coordinate in radians."}],"identifier":"doc:\/\/com.applayr.MapLayr\/documentation\/MapLayr\/MapView\/angle(at:heading:)-3rwxm","type":"topic"},"doc://com.applayr.MapLayr/documentation/MapLayr/MapView/mapData":{"url":"\/documentation\/maplayr\/mapview\/mapdata","identifier":"doc:\/\/com.applayr.MapLayr\/documentation\/MapLayr\/MapView\/mapData","fragments":[{"kind":"keyword","text":"var"},{"kind":"text","text":" "},{"kind":"identifier","text":"mapData"},{"kind":"text","text":": "},{"kind":"typeIdentifier","text":"MapData","preciseIdentifier":"s:15MapLayrInternal0A4DataV"},{"kind":"text","text":"?"}],"kind":"symbol","title":"mapData","type":"topic","role":"symbol","abstract":[{"type":"text","text":"The specific map data version that the map view uses."}]},"doc://com.applayr.MapLayr/objc(pl)CALayerDelegate":{"type":"unresolvable","identifier":"doc:\/\/com.applayr.MapLayr\/objc(pl)CALayerDelegate","title":"QuartzCore.CALayerDelegate"},"doc://com.applayr.MapLayr/documentation/MapLayr/MapView/insertMapLayer(_:at:)":{"abstract":[{"text":"Inserts the specified map layer at the given position.","type":"text"}],"role":"symbol","fragments":[{"kind":"keyword","text":"func"},{"kind":"text","text":" "},{"kind":"identifier","text":"insertMapLayer"},{"kind":"text","text":"(any "},{"kind":"typeIdentifier","preciseIdentifier":"s:15MapLayrInternal0A5LayerP","text":"MapLayer"},{"kind":"text","text":", "},{"kind":"externalParam","text":"at"},{"kind":"text","text":": "},{"kind":"typeIdentifier","preciseIdentifier":"s:Si","text":"Int"},{"kind":"text","text":")"}],"title":"insertMapLayer(_:at:)","type":"topic","identifier":"doc:\/\/com.applayr.MapLayr\/documentation\/MapLayr\/MapView\/insertMapLayer(_:at:)","kind":"symbol","url":"\/documentation\/maplayr\/mapview\/insertmaplayer(_:at:)"},"doc://com.applayr.MapLayr/objc(pl)UILargeContentViewerItem":{"type":"unresolvable","identifier":"doc:\/\/com.applayr.MapLayr\/objc(pl)UILargeContentViewerItem","title":"UIKit.UILargeContentViewerItem"},"doc://com.applayr.MapLayr/documentation/MapLayr/MapView/span":{"abstract":[{"type":"text","text":"The current span of the camera in metres."}],"role":"symbol","fragments":[{"kind":"keyword","text":"var"},{"kind":"text","text":" "},{"kind":"identifier","text":"span"},{"kind":"text","text":": "},{"kind":"typeIdentifier","text":"Distance","preciseIdentifier":"s:11MapGeometry8Distancea"}],"title":"span","type":"topic","identifier":"doc:\/\/com.applayr.MapLayr\/documentation\/MapLayr\/MapView\/span","kind":"symbol","url":"\/documentation\/maplayr\/mapview\/span"},"doc://com.applayr.MapLayr/documentation/MapLayr/MapView/coordinates":{"abstract":[{"text":"Returns the camera’s current coordinates.","type":"text"}],"kind":"symbol","fragments":[{"text":"var","kind":"keyword"},{"text":" ","kind":"text"},{"text":"coordinates","kind":"identifier"},{"text":": ","kind":"text"},{"preciseIdentifier":"s:11MapGeometry11CoordinatesV","text":"Coordinates","kind":"typeIdentifier"}],"url":"\/documentation\/maplayr\/mapview\/coordinates","title":"coordinates","role":"symbol","type":"topic","identifier":"doc:\/\/com.applayr.MapLayr\/documentation\/MapLayr\/MapView\/coordinates"}}}